{"0":{"full_name":"Mahdi karimian","email":"karimian@gmail.com","mobile":"09121112222","password":"$2y$10$NNvlMk9xQ5L\/OiviHW8IPu6PNmOV9fjdpgvYcx9EdNMb8cylCIHw6","id":900},"6":{"full_name":"Mahdi karimian","email":"karimian@gmail.com","mobile":"09121112222","password":"$2y$10$BupWRJMTnA82heR5GkRj4.mYL1kyRH7WeMvSjngiCpLhBwPa1zAuS","id":69},"7":{"full_name":"amiiiirr","email":"aliiiii@gmail.com","mobile":"09121112222","password":"$2y$10$raHcnK.zQbt\/4JOsDDW4kOlMPhIIiv9C.JldhSILU7WGu5Gkm5OC6","id":252}}